{
  "title": "This Month Report",
  "period": {
    "start": "2026-05-01",
    "end": "2026-05-06"
  },
  "generated": "2026-05-06 09:29:30",
  "metrics": {
    "total_revenue": 16340.0,
    "total_notas": 5,
    "avg_ticket": 3268.0,
    "total_items": 10
  },
  "top_customers": [
    {
      "rank": 1,
      "name": "Alejandro",
      "revenue": 11700.0
    },
    {
      "rank": 2,
      "name": "Tacos memo",
      "revenue": 2820.0
    },
    {
      "rank": 3,
      "name": "Los papis",
      "revenue": 1820.0
    }
  ],
  "top_products": [
    {
      "rank": 1,
      "name": "Arrachera marinada",
      "quantity": 122
    },
    {
      "rank": 2,
      "name": "Bistec de cerdo entero",
      "quantity": 25
    },
    {
      "rank": 3,
      "name": "Aguja marinada",
      "quantity": 22
    },
    {
      "rank": 4,
      "name": "Bistec picado",
      "quantity": 10
    },
    {
      "rank": 5,
      "name": "Ribeye",
      "quantity": 0.8
    }
  ],
  "records": [
    {
      "Timestamp": "5/1/2026 20:03:55",
      "Remision": "20260501-1202",
      "Fecha": "2026-05-01",
      "Cliente": "Alejandro",
      "ClienteEmail": "",
      "Ciudad": "Querétaro",
      "Conceptos_JSON": "[{\"cantidad\":60,\"descripcion\":\"Arrachera marinada\",\"pu\":81,\"importe\":4860},{\"cantidad\":25,\"descripcion\":\"Bistec de cerdo entero\",\"pu\":80,\"importe\":2000},{\"cantidad\":0.8,\"descripcion\":\"Ribeye\",\"pu\":260,\"importe\":208},{\"cantidad\":0.8,\"descripcion\":\"New York\",\"pu\":240,\"importe\":192}]",
      "Subtotal": 7260,
      "IVA": 0,
      "Descuento": 0,
      "Total": 7260
    },
    {
      "Timestamp": "5/4/2026 16:22:46",
      "Remision": "20260504-0822",
      "Fecha": "2026-05-04",
      "Cliente": "Alejandro",
      "ClienteEmail": "",
      "Ciudad": "Querétaro",
      "Conceptos_JSON": "[{\"cantidad\":40,\"descripcion\":\"Arrachera marinada\",\"pu\":81,\"importe\":3240},{\"cantidad\":10,\"descripcion\":\"Aguja marinada\",\"pu\":120,\"importe\":1200}]",
      "Subtotal": 4440,
      "IVA": 0,
      "Descuento": 0,
      "Total": 4440
    },
    {
      "Timestamp": "5/4/2026 16:24:21",
      "Remision": "20260504-0823",
      "Fecha": "2026-05-04",
      "Cliente": "Los papis",
      "ClienteEmail": "",
      "Ciudad": "Querétaro",
      "Conceptos_JSON": "[{\"cantidad\":10,\"descripcion\":\"Arrachera marinada\",\"pu\":90,\"importe\":900}]",
      "Subtotal": 900,
      "IVA": 0,
      "Descuento": 0,
      "Total": 900
    },
    {
      "Timestamp": "5/6/2026 0:48:21",
      "Remision": "20260505-1648",
      "Fecha": "2026-05-05",
      "Cliente": "Los papis",
      "ClienteEmail": "",
      "Ciudad": "Querétaro",
      "Conceptos_JSON": "[{\"cantidad\":10,\"descripcion\":\"Bistec picado\",\"pu\":92,\"importe\":920}]",
      "Subtotal": 920,
      "IVA": 0,
      "Descuento": 0,
      "Total": 920
    },
    {
      "Timestamp": "5/6/2026 1:23:40",
      "Remision": "20260505-1723",
      "Fecha": "2026-05-05",
      "Cliente": "Tacos memo",
      "ClienteEmail": "",
      "Ciudad": "Querétaro",
      "Conceptos_JSON": "[{\"cantidad\":12,\"descripcion\":\"Aguja marinada\",\"pu\":135,\"importe\":1620},{\"cantidad\":12,\"descripcion\":\"Arrachera marinada\",\"pu\":100,\"importe\":1200}]",
      "Subtotal": 2820,
      "IVA": 0,
      "Descuento": 0,
      "Total": 2820
    }
  ]
}